[
  {
    "description": "",
    "elements": [
      {
        "description": "",
        "id": "user-authentication-tests;",
        "keyword": "Scenario",
        "line": 4,
        "name": "",
        "steps": [
          {
            "arguments": [],
            "keyword": "Given ",
            "line": 5,
            "name": "User opens the login page",
            "match": {
              "location": "src/tests/steps/registrationSteps.ts:12"
            },
            "result": {
              "status": "passed",
              "duration": 7050713166
            }
          },
          {
            "arguments": [],
            "keyword": "When ",
            "line": 6,
            "name": "User clicks on the Login button",
            "match": {
              "location": "src/tests/steps/registrationSteps.ts:19"
            },
            "result": {
              "status": "passed",
              "duration": 53488999
            }
          },
          {
            "arguments": [],
            "keyword": "Then ",
            "line": 7,
            "name": "User should be redirected to the login page",
            "match": {
              "location": "src/tests/steps/registrationSteps.ts:23"
            },
            "result": {
              "status": "passed",
              "duration": 325325208
            }
          },
          {
            "arguments": [],
            "keyword": "Given ",
            "line": 9,
            "name": "User goes to the registration page",
            "match": {
              "location": "src/tests/steps/registrationSteps.ts:27"
            },
            "result": {
              "status": "passed",
              "duration": 210297125
            }
          },
          {
            "arguments": [],
            "keyword": "When ",
            "line": 10,
            "name": "User clicks the First name field",
            "match": {
              "location": "src/tests/steps/registrationSteps.ts:31"
            },
            "result": {
              "status": "passed",
              "duration": 43139375
            }
          },
          {
            "arguments": [],
            "keyword": "Then ",
            "line": 11,
            "name": "User fills in the First name field with correct values and values are visible",
            "match": {
              "location": "src/tests/steps/registrationSteps.ts:35"
            },
            "result": {
              "status": "passed",
              "duration": 10490417
            }
          },
          {
            "arguments": [],
            "keyword": "When ",
            "line": 13,
            "name": "User clicks the Last name field",
            "match": {
              "location": "src/tests/steps/registrationSteps.ts:45"
            },
            "result": {
              "status": "passed",
              "duration": 22158666
            }
          },
          {
            "arguments": [],
            "keyword": "Then ",
            "line": 14,
            "name": "User fills in the Last name field with correct values and values are visible",
            "match": {
              "location": "src/tests/steps/registrationSteps.ts:49"
            },
            "result": {
              "status": "passed",
              "duration": 12807375
            }
          },
          {
            "arguments": [],
            "keyword": "When ",
            "line": 16,
            "name": "User clicks the Password field",
            "match": {
              "location": "src/tests/steps/registrationSteps.ts:73"
            },
            "result": {
              "status": "passed",
              "duration": 28623833
            }
          },
          {
            "arguments": [],
            "keyword": "Then ",
            "line": 17,
            "name": "User fills in the Password field with correct values and values are visible",
            "match": {
              "location": "src/tests/steps/registrationSteps.ts:77"
            },
            "result": {
              "status": "passed",
              "duration": 7548875
            }
          },
          {
            "arguments": [],
            "keyword": "When ",
            "line": 19,
            "name": "User clicks the Confirm Password field",
            "match": {
              "location": "src/tests/steps/registrationSteps.ts:87"
            },
            "result": {
              "status": "passed",
              "duration": 25416250
            }
          },
          {
            "arguments": [],
            "keyword": "Then ",
            "line": 20,
            "name": "User fills in the Confirm Password field with correct values and values are visible",
            "match": {
              "location": "src/tests/steps/registrationSteps.ts:91"
            },
            "result": {
              "status": "passed",
              "duration": 6417583
            }
          },
          {
            "arguments": [],
            "keyword": "When ",
            "line": 22,
            "name": "User selects the Gender checkbox as a Male",
            "match": {
              "location": "src/tests/steps/registrationSteps.ts:101"
            },
            "result": {
              "status": "passed",
              "duration": 28017749
            }
          },
          {
            "arguments": [],
            "keyword": "Then ",
            "line": 23,
            "name": "User's Gender selected and visible",
            "result": {
              "status": "undefined",
              "duration": 0
            }
          },
          {
            "arguments": [],
            "keyword": "When ",
            "line": 25,
            "name": "User clicks the Register button",
            "match": {
              "location": "src/tests/steps/registrationSteps.ts:105"
            },
            "result": {
              "status": "skipped",
              "duration": 0
            }
          },
          {
            "arguments": [],
            "keyword": "Then ",
            "line": 26,
            "name": "User redirected to the login page and registered successfully",
            "result": {
              "status": "undefined",
              "duration": 0
            }
          },
          {
            "keyword": "After",
            "hidden": true,
            "result": {
              "status": "passed",
              "duration": 73254917
            }
          }
        ],
        "tags": [
          {
            "name": "@registration",
            "line": 3
          }
        ],
        "type": "scenario"
      }
    ],
    "id": "user-authentication-tests",
    "line": 1,
    "keyword": "Feature",
    "name": "User Authentication tests",
    "tags": [],
    "uri": "src/tests/features/registration.feature"
  }
]